blazogram/__init__.py
blazogram/enums.py
blazogram/exceptions.py
blazogram/bot/__init__.py
blazogram/bot/bot.py
blazogram/bot/methods.py
blazogram/database/__init__.py
blazogram/database/base.py
blazogram/database/memory.py
blazogram/database/postgres.py
blazogram/database/sqlite.py
blazogram/dispatcher/__init__.py
blazogram/dispatcher/dispatcher.py
blazogram/dispatcher/router.py
blazogram/dispatcher/telegram_update.py
blazogram/filters/__init__.py
blazogram/filters/base.py
blazogram/filters/chat_type.py
blazogram/filters/command.py
blazogram/filters/content_type.py
blazogram/filters/data.py
blazogram/filters/state_filter.py
blazogram/filters/text.py
blazogram/filters/user_filter.py
blazogram/fsm/__init__.py
blazogram/fsm/context.py
blazogram/fsm/state.py
blazogram/fsm/storage/base.py
blazogram/fsm/storage/memory.py
blazogram/fsm/storage/redis.py
blazogram/middlewares/__init__.py
blazogram/middlewares/base.py
blazogram/middlewares/database.py
blazogram/middlewares/handler_middlewares.py
blazogram/middlewares/throttling.py
blazogram/scheduler/__init__.py
blazogram/scheduler/scheduler.py
blazogram/scheduler/storage/base.py
blazogram/scheduler/storage/memory.py
blazogram/scheduler/storage/sqlite.py
blazogram/types/__init__.py
blazogram/types/callback_query.py
blazogram/types/chat.py
blazogram/types/inline_keyboard.py
blazogram/types/input_file.py
blazogram/types/message.py
blazogram/types/photo.py
blazogram/types/reply_keyboard.py
blazogram/types/update.py
blazogram/types/user.py
blazogram/types/video.py
blazogram-2.1.dist-info/METADATA
blazogram-2.1.dist-info/WHEEL
blazogram-2.1.dist-info/top_level.txt
blazogram-2.1.dist-info/RECORD
