Metadata-Version: 2.1
Name: blazogram
Version: 2.1
Summary: BLAZOGRAM - is a library for make Telegram Bots
Author-email: EgorBlaze <blazeegor@gmail.com>
Project-URL: Homepage, https://github.com/blazeegor/blazogram
Project-URL: Bug Tracker, https://github.com/blazeegor/blazogram/issues
Classifier: Programming Language :: Python :: 3
Classifier: License :: OSI Approved :: MIT License
Classifier: Operating System :: OS Independent
Requires-Python: >=3.8
Requires-Dist: aiohttp
Requires-Dist: redis
Requires-Dist: asyncpg
Requires-Dist: aiosqlite
Requires-Dist: locute
